dtool/__init__.py
dtool/version.py
dtool-3.27.0.dist-info/LICENSE.rst
dtool-3.27.0.dist-info/METADATA
dtool-3.27.0.dist-info/WHEEL
dtool-3.27.0.dist-info/top_level.txt
dtool-3.27.0.dist-info/RECORD
