Metadata-Version: 2.1
Name: dtool
Version: 3.27.0
Summary: dtool command line client for managing data
Author-email: Tjelvar Olsson <tjelvar.olsson@gmail.com>
Project-URL: Documentation, https://dtool.readthedocs.io
Project-URL: Repository, https://github.com/jic-dtool/dtool
Project-URL: Changelog, https://github.com/jic-dtool/dtool/blob/master/CHANGELOG.rst
License-File: LICENSE.rst
Requires-Dist: dtoolcore ==3.18.3
Requires-Dist: dtool-cli ==0.7.1
Requires-Dist: dtool-create ==0.23.4
Requires-Dist: dtool-info ==0.16.2
Requires-Dist: dtool-symlink ==0.3.1
Requires-Dist: dtool-http ==0.5.1
Requires-Dist: dtool-config ==0.4.1
Requires-Dist: dtool-overlay ==0.3.1
Requires-Dist: dtool-annotation ==0.1.1
Requires-Dist: dtool-tag ==0.1.1
Provides-Extra: docs
Requires-Dist: sphinx ; extra == 'docs'
Requires-Dist: sphinx-rtd-theme ; extra == 'docs'
Provides-Extra: test
Requires-Dist: pytest ; extra == 'test'
Requires-Dist: pytest-cov ; extra == 'test'
